Metadata-Version: 1.1
Name: NMMSO
Version: 1.0.1
Summary: Python Implementation of the Niching Migratory Multi-Swarm Optimizer
Home-page: UNKNOWN
Author: Varchas Gopalaswamy
Author-email: vgop@lle.rochester.edu
License: MIT
Download-URL: https://github.com/varchasgopalaswamy/NMMSO/archive/1.0.tar.gz
Keywords: optimizer,black,box,black-box,optimize,swarm,particle,niching,multi-modal
Platform: UNKNOWN
Classifier: Development Status :: 4 - Beta
Classifier: Programming Language :: Python :: 3.5
Classifier: Programming Language :: Python :: 3.6
